MANIFEST.in
README.rst
requirements.txt
setup.cfg
setup.py
django_dynamite.egg-info/PKG-INFO
django_dynamite.egg-info/SOURCES.txt
django_dynamite.egg-info/dependency_links.txt
django_dynamite.egg-info/requires.txt
django_dynamite.egg-info/top_level.txt
docs/admin.rst
docs/conf.py
docs/examples.rst
docs/index.rst
docs/models.rst
docs/signals.rst
dynamite/__init__.py
dynamite/admin.py
dynamite/db.py
dynamite/fields.py
dynamite/handlers.py
dynamite/models.py
dynamite/registry.py
dynamite/signals.py
example/__init__.py
example/manage.py
example/settings.py
example/urls.py
example/skill/__init__.py
example/skill/admin.py
example/skill/models.py
example/survey/__init__.py
example/survey/admin.py
example/survey/models.py
example/survey/tests.py
example/survey/fixtures/initial_data.json