Metadata-Version: 1.0
Name: django-dynamite
Version: 0.4.1
Summary: Dynamic models framework
